pyproject.toml
setup.py
twincharm.egg-info/PKG-INFO
twincharm.egg-info/SOURCES.txt
twincharm.egg-info/dependency_links.txt
twincharm.egg-info/top_level.txt
twincharm/client/objtrans/__init__.py
twincharm/client/rpc/__init__.py
twincharm/response/__init__.py
twincharm/server/objtrans/__init__.py
twincharm/server/rpc/__init__.py