Metadata-Version: 1.0
Name: twincharm
Version: 1.1.1
Summary:  RPC and Object Transfer library.
Home-page: https://github.com/jenca-adam
Author: Adam Jenča
Author-email: jenca.a@gjh.sk
License: UNKNOWN
Platform: UNKNOWN
